automation/__init__.py
automation/buffer.py
automation/core.py
automation/models.py
automation/singleton.py
automation/state_machine.py
automation/alarms/__init__.py
automation/alarms/states.py
automation/alarms/trigger.py
automation/dbmodels/__init__.py
automation/dbmodels/alarms.py
automation/dbmodels/core.py
automation/dbmodels/events.py
automation/dbmodels/logs.py
automation/dbmodels/machines.py
automation/dbmodels/opcua.py
automation/dbmodels/opcua_server.py
automation/dbmodels/tags.py
automation/dbmodels/users.py
automation/extensions/__init__.py
automation/extensions/api.py
automation/extensions/cors.py
automation/filter/__init__.py
automation/hmi/index.html
automation/hmi/assets/bootstrap-icons-BeopsB42.woff
automation/hmi/assets/bootstrap-icons-mSm7cUeB.woff2
automation/hmi/assets/fa-brands-400-D1LuMI3I.ttf
automation/hmi/assets/fa-brands-400-D_cYUPeE.woff2
automation/hmi/assets/fa-regular-400-BjRzuEpd.woff2
automation/hmi/assets/fa-regular-400-DZaxPHgR.ttf
automation/hmi/assets/fa-solid-900-CTAAxXor.woff2
automation/hmi/assets/fa-solid-900-D0aA9rwL.ttf
automation/hmi/assets/fa-v4compatibility-C9RhG_FT.woff2
automation/hmi/assets/fa-v4compatibility-CCth-dXg.ttf
automation/hmi/assets/index-0YbKFUUP.js
automation/hmi/assets/index-fe9Q2n8A.css
automation/hmi/industrial_pallete_icons/90° curve 2.svg
automation/hmi/industrial_pallete_icons/Analog gauge.svg
automation/hmi/industrial_pallete_icons/Cool pump.svg
automation/hmi/industrial_pallete_icons/Hand valve 4.svg
automation/hmi/industrial_pallete_icons/Mass flowmeter.svg
automation/hmi/industrial_pallete_icons/Short horizontal pipe.svg
automation/hmi/industrial_pallete_icons/Tank 16.svg
automation/iad/__init__.py
automation/iad/frozen_data.py
automation/iad/out_of_range.py
automation/iad/outliers.py
automation/logger/__init__.py
automation/logger/alarms.py
automation/logger/core.py
automation/logger/datalogger.py
automation/logger/events.py
automation/logger/logdict.py
automation/logger/logs.py
pyautomationio-2.0.11.dist-info/licenses/LICENSE
pyautomationio-2.0.11.dist-info/METADATA
pyautomationio-2.0.11.dist-info/WHEEL
pyautomationio-2.0.11.dist-info/top_level.txt
pyautomationio-2.0.11.dist-info/RECORD
