Metadata-Version: 2.4
Name: PyAutomationIO
Version: 2.0.11
Summary: A python framework to develop automation industrial processes applications and Artificial Intelligence applications for the industrial field
Home-page: https://github.com/know-ai/PyAutomation
Author: KnowAI
Author-email: dev.know.ai@gmail.com
License: GNU AFFERO GENERAL PUBLIC LICENSE
Classifier: Programming Language :: Python :: 3.10
Classifier: Programming Language :: Python :: 3.11
Classifier: Programming Language :: Python :: 3.12
Classifier: Programming Language :: Python :: 3.13
Classifier: Programming Language :: Python :: 3.14
Classifier: License :: OSI Approved :: GNU Affero General Public License v3
Classifier: Operating System :: OS Independent
Classifier: Topic :: Software Development :: Libraries
Classifier: Topic :: System :: Logging
Classifier: Topic :: System :: Monitoring
License-File: LICENSE
Requires-Dist: python-statemachine==2.4.0
Requires-Dist: python-statemachine[diagrams]
Requires-Dist: peewee==3.18.3
Requires-Dist: psycopg2-binary==2.9.9; sys_platform != "win32" and python_version >= "3.9" and python_version <= "3.11"
Requires-Dist: psycopg2-binary==2.9.11; sys_platform != "win32" and python_version > "3.11" and python_version <= "3.13"
Requires-Dist: numpy==1.25.0; python_version <= "3.11"
Requires-Dist: numpy==1.26.0; python_version == "3.12"
Requires-Dist: numpy==2.0.0; python_version == "3.13"
Requires-Dist: numpy==2.1.0; python_version >= "3.14"
Requires-Dist: PyWavelets==1.6.0; python_version == "3.9"
Requires-Dist: PyWavelets==1.7.0; python_version >= "3.10" and python_version <= "3.11"
Requires-Dist: PyWavelets==1.9.0; python_version >= "3.12" and python_version <= "3.14"
Requires-Dist: opcua==0.98.13
Requires-Dist: python-dotenv==1.2.1
Requires-Dist: cryptography==43.0.3
Requires-Dist: Flask==3.1.2
Requires-Dist: requests==2.32.5
Requires-Dist: Flask-Cors==6.0.1
Requires-Dist: flask-restx==1.3.2
Requires-Dist: Flask-SocketIO==5.5.1
Requires-Dist: gunicorn==23.0.0
Requires-Dist: websocket-client==1.9.0
Requires-Dist: gevent-websocket==0.10.1
Requires-Dist: PyJWT==2.10.1
Dynamic: author
Dynamic: author-email
Dynamic: classifier
Dynamic: description
Dynamic: description-content-type
Dynamic: home-page
Dynamic: license
Dynamic: license-file
Dynamic: requires-dist
Dynamic: summary
